{
  "1721467760183": [
    { "title": "Vue2.5开发去哪儿网App", "count": 12 },
    { "title": "React 16.4 开发简书项目", "count": 63 },
    { "title": "React服务器渲染原理解析与实践", "count": 37 },
    { "title": "手把手带你掌握新版Webpack4.0", "count": 24 }
  ],
  "1721467782440": [
    { "title": "Vue2.5开发去哪儿网App", "count": 52 },
    { "title": "React 16.4 开发简书项目", "count": 41 },
    { "title": "React服务器渲染原理解析与实践", "count": 70 },
    { "title": "手把手带你掌握新版Webpack4.0", "count": 40 }
  ],
  "1721477433557": [
    { "title": "Vue2.5开发去哪儿网App", "count": 13 },
    { "title": "React 16.4 开发简书项目", "count": 30 },
    { "title": "React服务器渲染原理解析与实践", "count": 59 },
    { "title": "手把手带你掌握新版Webpack4.0", "count": 66 }
  ],
  "1721477454003": [
    { "title": "Vue2.5开发去哪儿网App", "count": 25 },
    { "title": "React 16.4 开发简书项目", "count": 100 },
    { "title": "React服务器渲染原理解析与实践", "count": 33 },
    { "title": "手把手带你掌握新版Webpack4.0", "count": 8 }
  ]
}
